{
    "annotations": {
        "list": []
    },
    "description": "MultigresCluster topology health: cluster phase, cell gateways, shard pools, and TopoServer",
    "editable": true,
    "fiscalYearStartMonth": 0,
    "graphTooltip": 1,
    "links": [],
    "panels": [
        {
            "collapsed": false,
            "gridPos": {
                "h": 1,
                "w": 24,
                "x": 0,
                "y": 0
            },
            "id": 100,
            "title": "Cluster Overview",
            "type": "row"
        },
        {
            "datasource": {
                "type": "prometheus",
                "uid": "prometheus-uid"
            },
            "fieldConfig": {
                "defaults": {
                    "color": {
                        "mode": "fixed",
                        "fixedColor": "text"
                    },
                    "custom": {
                        "align": "center",
                        "cellOptions": {
                            "type": "color-text"
                        }
                    },
                    "mappings": [],
                    "thresholds": {
                        "mode": "absolute",
                        "steps": [
                            {
                                "color": "green",
                                "value": null
                            }
                        ]
                    }
                },
                "overrides": [
                    {
                        "matcher": {
                            "id": "byName",
                            "options": "phase"
                        },
                        "properties": [
                            {
                                "id": "mappings",
                                "value": [
                                    {
                                        "type": "value",
                                        "options": {
                                            "Healthy": {
                                                "color": "green",
                                                "text": "Healthy"
                                            },
                                            "Provisioning": {
                                                "color": "yellow",
                                                "text": "Provisioning"
                                            },
                                            "Degraded": {
                                                "color": "orange",
                                                "text": "Degraded"
                                            },
                                            "Error": {
                                                "color": "red",
                                                "text": "Error"
                                            }
                                        }
                                    }
                                ]
                            },
                            {
                                "id": "custom.cellOptions",
                                "value": {
                                    "type": "color-text"
                                }
                            }
                        ]
                    },
                    {
                        "matcher": {
                            "id": "byName",
                            "options": "Value"
                        },
                        "properties": [
                            {
                                "id": "custom.hidden",
                                "value": true
                            }
                        ]
                    }
                ]
            },
            "gridPos": {
                "h": 6,
                "w": 24,
                "x": 0,
                "y": 1
            },
            "id": 1,
            "options": {
                "showHeader": true,
                "sortBy": [
                    {
                        "displayName": "name"
                    }
                ]
            },
            "title": "Cluster Phases",
            "type": "table",
            "targets": [
                {
                    "datasource": {
                        "type": "prometheus",
                        "uid": "prometheus-uid"
                    },
                    "expr": "multigres_operator_cluster_info == 1",
                    "format": "table",
                    "instant": true
                }
            ],
            "transformations": [
                {
                    "id": "filterFieldsByName",
                    "options": {
                        "include": {
                            "names": [
                                "name",
                                "namespace",
                                "phase"
                            ]
                        }
                    }
                }
            ]
        },
        {
            "datasource": {
                "type": "prometheus",
                "uid": "prometheus-uid"
            },
            "fieldConfig": {
                "defaults": {
                    "color": {
                        "mode": "palette-classic"
                    },
                    "custom": {
                        "axisBorderShow": false,
                        "axisCenteredZero": false,
                        "drawStyle": "line",
                        "fillOpacity": 15,
                        "gradientMode": "opacity",
                        "lineWidth": 2,
                        "pointSize": 5,
                        "showPoints": "never",
                        "spanNulls": false,
                        "stacking": {
                            "mode": "none"
                        }
                    },
                    "unit": "short"
                }
            },
            "gridPos": {
                "h": 8,
                "w": 12,
                "x": 0,
                "y": 7
            },
            "id": 2,
            "options": {
                "legend": {
                    "calcs": [
                        "lastNotNull"
                    ],
                    "displayMode": "table",
                    "placement": "bottom"
                },
                "tooltip": {
                    "mode": "multi",
                    "sort": "desc"
                }
            },
            "title": "Cells per Cluster",
            "type": "timeseries",
            "targets": [
                {
                    "datasource": {
                        "type": "prometheus",
                        "uid": "prometheus-uid"
                    },
                    "expr": "multigres_operator_cluster_cells_total",
                    "legendFormat": "{{cluster}} ({{namespace}})"
                }
            ]
        },
        {
            "datasource": {
                "type": "prometheus",
                "uid": "prometheus-uid"
            },
            "fieldConfig": {
                "defaults": {
                    "color": {
                        "mode": "palette-classic"
                    },
                    "custom": {
                        "axisBorderShow": false,
                        "axisCenteredZero": false,
                        "drawStyle": "line",
                        "fillOpacity": 15,
                        "gradientMode": "opacity",
                        "lineWidth": 2,
                        "pointSize": 5,
                        "showPoints": "never",
                        "spanNulls": false,
                        "stacking": {
                            "mode": "none"
                        }
                    },
                    "unit": "short"
                }
            },
            "gridPos": {
                "h": 8,
                "w": 12,
                "x": 12,
                "y": 7
            },
            "id": 3,
            "options": {
                "legend": {
                    "calcs": [
                        "lastNotNull"
                    ],
                    "displayMode": "table",
                    "placement": "bottom"
                },
                "tooltip": {
                    "mode": "multi",
                    "sort": "desc"
                }
            },
            "title": "Shards per Cluster",
            "type": "timeseries",
            "targets": [
                {
                    "datasource": {
                        "type": "prometheus",
                        "uid": "prometheus-uid"
                    },
                    "expr": "multigres_operator_cluster_shards_total",
                    "legendFormat": "{{cluster}} ({{namespace}})"
                }
            ]
        },
        {
            "collapsed": false,
            "gridPos": {
                "h": 1,
                "w": 24,
                "x": 0,
                "y": 15
            },
            "id": 101,
            "title": "Cell Gateways",
            "type": "row"
        },
        {
            "datasource": {
                "type": "prometheus",
                "uid": "prometheus-uid"
            },
            "fieldConfig": {
                "defaults": {
                    "color": {
                        "mode": "palette-classic"
                    },
                    "custom": {
                        "axisBorderShow": false,
                        "axisCenteredZero": false,
                        "drawStyle": "line",
                        "fillOpacity": 15,
                        "gradientMode": "opacity",
                        "lineWidth": 2,
                        "pointSize": 5,
                        "showPoints": "never",
                        "spanNulls": false,
                        "stacking": {
                            "mode": "none"
                        }
                    },
                    "unit": "short"
                },
                "overrides": [
                    {
                        "matcher": {
                            "id": "byRegexp",
                            "options": ".*desired.*"
                        },
                        "properties": [
                            {
                                "id": "custom.lineStyle",
                                "value": {
                                    "fill": "dash",
                                    "dash": [
                                        10,
                                        10
                                    ]
                                }
                            }
                        ]
                    }
                ]
            },
            "gridPos": {
                "h": 8,
                "w": 24,
                "x": 0,
                "y": 16
            },
            "id": 4,
            "options": {
                "legend": {
                    "calcs": [
                        "lastNotNull"
                    ],
                    "displayMode": "table",
                    "placement": "bottom"
                },
                "tooltip": {
                    "mode": "multi",
                    "sort": "desc"
                }
            },
            "title": "MultiGateway Replicas (Desired vs Ready)",
            "type": "timeseries",
            "targets": [
                {
                    "datasource": {
                        "type": "prometheus",
                        "uid": "prometheus-uid"
                    },
                    "expr": "multigres_operator_cell_gateway_replicas{state=\"desired\"}",
                    "legendFormat": "{{cell}} desired"
                },
                {
                    "datasource": {
                        "type": "prometheus",
                        "uid": "prometheus-uid"
                    },
                    "expr": "multigres_operator_cell_gateway_replicas{state=\"ready\"}",
                    "legendFormat": "{{cell}} ready"
                }
            ]
        },
        {
            "collapsed": false,
            "gridPos": {
                "h": 1,
                "w": 24,
                "x": 0,
                "y": 24
            },
            "id": 102,
            "title": "Shard Pools",
            "type": "row"
        },
        {
            "datasource": {
                "type": "prometheus",
                "uid": "prometheus-uid"
            },
            "fieldConfig": {
                "defaults": {
                    "color": {
                        "mode": "palette-classic"
                    },
                    "custom": {
                        "axisBorderShow": false,
                        "axisCenteredZero": false,
                        "drawStyle": "line",
                        "fillOpacity": 15,
                        "gradientMode": "opacity",
                        "lineWidth": 2,
                        "pointSize": 5,
                        "showPoints": "never",
                        "spanNulls": false,
                        "stacking": {
                            "mode": "none"
                        }
                    },
                    "unit": "short"
                },
                "overrides": [
                    {
                        "matcher": {
                            "id": "byRegexp",
                            "options": ".*desired.*"
                        },
                        "properties": [
                            {
                                "id": "custom.lineStyle",
                                "value": {
                                    "fill": "dash",
                                    "dash": [
                                        10,
                                        10
                                    ]
                                }
                            }
                        ]
                    }
                ]
            },
            "gridPos": {
                "h": 8,
                "w": 24,
                "x": 0,
                "y": 25
            },
            "id": 5,
            "options": {
                "legend": {
                    "calcs": [
                        "lastNotNull"
                    ],
                    "displayMode": "table",
                    "placement": "bottom"
                },
                "tooltip": {
                    "mode": "multi",
                    "sort": "desc"
                }
            },
            "title": "Pool Replicas (Desired vs Ready)",
            "type": "timeseries",
            "targets": [
                {
                    "datasource": {
                        "type": "prometheus",
                        "uid": "prometheus-uid"
                    },
                    "expr": "multigres_operator_shard_pool_replicas{state=\"desired\"}",
                    "legendFormat": "{{shard}}/{{pool}} desired"
                },
                {
                    "datasource": {
                        "type": "prometheus",
                        "uid": "prometheus-uid"
                    },
                    "expr": "multigres_operator_shard_pool_replicas{state=\"ready\"}",
                    "legendFormat": "{{shard}}/{{pool}} ready"
                }
            ]
        },
        {
            "collapsed": false,
            "gridPos": {
                "h": 1,
                "w": 24,
                "x": 0,
                "y": 33
            },
            "id": 103,
            "title": "TopoServer",
            "type": "row"
        },
        {
            "datasource": {
                "type": "prometheus",
                "uid": "prometheus-uid"
            },
            "fieldConfig": {
                "defaults": {
                    "color": {
                        "mode": "palette-classic"
                    },
                    "custom": {
                        "axisBorderShow": false,
                        "axisCenteredZero": false,
                        "drawStyle": "line",
                        "fillOpacity": 15,
                        "gradientMode": "opacity",
                        "lineWidth": 2,
                        "pointSize": 5,
                        "showPoints": "never",
                        "spanNulls": false,
                        "stacking": {
                            "mode": "none"
                        }
                    },
                    "unit": "short"
                },
                "overrides": [
                    {
                        "matcher": {
                            "id": "byRegexp",
                            "options": ".*desired.*"
                        },
                        "properties": [
                            {
                                "id": "custom.lineStyle",
                                "value": {
                                    "fill": "dash",
                                    "dash": [
                                        10,
                                        10
                                    ]
                                }
                            }
                        ]
                    }
                ]
            },
            "gridPos": {
                "h": 8,
                "w": 24,
                "x": 0,
                "y": 34
            },
            "id": 6,
            "options": {
                "legend": {
                    "calcs": [
                        "lastNotNull"
                    ],
                    "displayMode": "table",
                    "placement": "bottom"
                },
                "tooltip": {
                    "mode": "multi",
                    "sort": "desc"
                }
            },
            "title": "TopoServer Replicas (Desired vs Ready)",
            "type": "timeseries",
            "targets": [
                {
                    "datasource": {
                        "type": "prometheus",
                        "uid": "prometheus-uid"
                    },
                    "expr": "multigres_operator_toposerver_replicas{state=\"desired\"}",
                    "legendFormat": "{{name}} desired"
                },
                {
                    "datasource": {
                        "type": "prometheus",
                        "uid": "prometheus-uid"
                    },
                    "expr": "multigres_operator_toposerver_replicas{state=\"ready\"}",
                    "legendFormat": "{{name}} ready"
                }
            ]
        }
    ],
    "schemaVersion": 39,
    "tags": [
        "multigres",
        "cluster",
        "kubernetes"
    ],
    "templating": {
        "list": []
    },
    "time": {
        "from": "now-1h",
        "to": "now"
    },
    "timepicker": {},
    "timezone": "browser",
    "title": "Multigres Cluster Health",
    "uid": "multigres-cluster-health",
    "version": 1
}
